lightargs/__init__.py
lightargs/argument.py
lightargs/bright_args.py
lightargs/lightcoloring.py
lightargs/unknown_argument.py
lightargs/wrong_parameters.py
lightargs-1.27.dist-info/LICENSE
lightargs-1.27.dist-info/METADATA
lightargs-1.27.dist-info/WHEEL
lightargs-1.27.dist-info/top_level.txt
lightargs-1.27.dist-info/zip-safe
lightargs-1.27.dist-info/RECORD
