Metadata-Version: 2.1
Name: lightargs
Version: 1.27
Summary: simple arguments manager for python
Home-page: https://github.com/vincentberenz/lightargs.git
Author: Vincent Berenz
Author-email: vberenz@tuebingen.mpg.de
License: MIT
Keywords: arguments parser
Platform: UNKNOWN
Classifier: License :: OSI Approved :: MIT License
Classifier: Programming Language :: Python :: 2.7
Classifier: Programming Language :: Python :: 3
Requires-Dist: argcomplete
Requires-Dist: colorama
